sahara/__init__.py
sahara/config.py
sahara/context.py
sahara/exceptions.py
sahara/i18n.py
sahara/main.py
sahara/version.py
sahara/api/__init__.py
sahara/api/acl.py
sahara/api/base.py
sahara/api/microversion.py
sahara/api/v10.py
sahara/api/v11.py
sahara/api/middleware/__init__.py
sahara/api/middleware/auth_valid.py
sahara/api/middleware/sahara_middleware.py
sahara/api/middleware/version_discovery.py
sahara/api/v2/__init__.py
sahara/api/v2/cluster_templates.py
sahara/api/v2/clusters.py
sahara/api/v2/data_sources.py
sahara/api/v2/images.py
sahara/api/v2/job_binaries.py
sahara/api/v2/job_templates.py
sahara/api/v2/job_types.py
sahara/api/v2/jobs.py
sahara/api/v2/node_group_templates.py
sahara/api/v2/plugins.py
sahara/cli/__init__.py
sahara/cli/sahara_all.py
sahara/cli/sahara_api.py
sahara/cli/sahara_engine.py
sahara/cli/sahara_status.py
sahara/cli/sahara_subprocess.py
sahara/cli/image_pack/__init__.py
sahara/cli/image_pack/api.py
sahara/cli/image_pack/cli.py
sahara/common/__init__.py
sahara/common/config.py
sahara/common/policies/__init__.py
sahara/common/policies/base.py
sahara/common/policies/cluster.py
sahara/common/policies/cluster_template.py
sahara/common/policies/cluster_templates.py
sahara/common/policies/clusters.py
sahara/common/policies/data_source.py
sahara/common/policies/data_sources.py
sahara/common/policies/image.py
sahara/common/policies/images.py
sahara/common/policies/job.py
sahara/common/policies/job_binaries.py
sahara/common/policies/job_binary.py
sahara/common/policies/job_binary_internals.py
sahara/common/policies/job_executions.py
sahara/common/policies/job_template.py
sahara/common/policies/job_type.py
sahara/common/policies/job_types.py
sahara/common/policies/jobs.py
sahara/common/policies/node_group_template.py
sahara/common/policies/node_group_templates.py
sahara/common/policies/plugin.py
sahara/common/policies/plugins.py
sahara/conductor/__init__.py
sahara/conductor/api.py
sahara/conductor/manager.py
sahara/conductor/objects.py
sahara-19.0.0.dist-info/AUTHORS
sahara-19.0.0.dist-info/LICENSE
sahara-19.0.0.dist-info/METADATA
sahara-19.0.0.dist-info/WHEEL
sahara-19.0.0.dist-info/entry_points.txt
sahara-19.0.0.dist-info/pbr.json
sahara-19.0.0.dist-info/top_level.txt
sahara-19.0.0.dist-info/RECORD
