Metadata-Version: 2.1
Name: sahara
Version: 19.0.0
Summary: Sahara project
Home-page: https://docs.openstack.org/sahara/latest/
Author: OpenStack
Author-email: openstack-discuss@lists.openstack.org
License: Apache Software License
Platform: UNKNOWN
Classifier: Programming Language :: Python
Classifier: Programming Language :: Python :: 3
Classifier: Programming Language :: Python :: 3.8
Classifier: Programming Language :: Python :: 3.9
Classifier: Environment :: OpenStack
Classifier: Intended Audience :: Information Technology
Classifier: Intended Audience :: System Administrators
Classifier: License :: OSI Approved :: Apache Software License
Classifier: Operating System :: POSIX :: Linux
Requires-Python: >=3.8
Requires-Dist: Flask (>=2.1.2)
Requires-Dist: Jinja2 (>=2.10)
Requires-Dist: SQLAlchemy (!=1.1.5,!=1.1.6,!=1.1.7,!=1.1.8,>=1.0.10)
Requires-Dist: WebOb (>=1.7.1)
Requires-Dist: alembic (>=0.9.6)
Requires-Dist: botocore (>=1.5.1)
Requires-Dist: castellan (>=0.16.0)
Requires-Dist: eventlet (>=0.26.0)
Requires-Dist: iso8601 (>=0.1.11)
Requires-Dist: jsonschema (>=3.2.0)
Requires-Dist: keystoneauth1 (>=3.4.0)
Requires-Dist: keystonemiddleware (>=4.17.0)
Requires-Dist: microversion-parse (>=0.2.1)
Requires-Dist: oslo.concurrency (>=3.26.0)
Requires-Dist: oslo.config (>=6.8.0)
Requires-Dist: oslo.context (>=2.22.0)
Requires-Dist: oslo.db (>=6.0.0)
Requires-Dist: oslo.i18n (>=3.20.0)
Requires-Dist: oslo.log (>=5.0.0)
Requires-Dist: oslo.messaging (>=14.1.0)
Requires-Dist: oslo.middleware (>=3.31.0)
Requires-Dist: oslo.policy (>=3.6.0)
Requires-Dist: oslo.rootwrap (>=5.8.0)
Requires-Dist: oslo.serialization (>=2.25.0)
Requires-Dist: oslo.service (>=1.31.0)
Requires-Dist: oslo.upgradecheck (>=1.3.0)
Requires-Dist: oslo.utils (>=4.5.0)
Requires-Dist: paramiko (>=2.7.1)
Requires-Dist: pbr (>=3.1.1)
Requires-Dist: python-cinderclient (!=4.0.0,>=3.3.0)
Requires-Dist: python-glanceclient (>=2.8.0)
Requires-Dist: python-heatclient (>=1.10.0)
Requires-Dist: python-keystoneclient (>=3.8.0)
Requires-Dist: python-manilaclient (>=1.16.0)
Requires-Dist: python-neutronclient (>=6.7.0)
Requires-Dist: python-novaclient (>=9.1.0)
Requires-Dist: python-swiftclient (>=3.2.0)
Requires-Dist: requests (>=2.23.0)
Requires-Dist: stevedore (>=1.20.0)
Requires-Dist: tooz (>=1.58.0)
